Workbook

Sheet Resumen
C2: FIDEICOMISOS PATRIMONIOS AUTÓNOMOS FIDUCIARIA LA PREVISORA S.A. FONDO DE PRESTACIONES SOCIALES DEL MAGISTERIO | E2: PROCESO: Administración de Servicios de Salud
C3: ='Detalle_ Radicacion'!C2 -> 0 | E3: CÓDIGO:
C4: ESTADO DE CUENTA POR PRESTADOR | E4: VERSIÓN: 06
B6: =CONCATENATE("Estado de cuenta por Prestador al ", TEXT(C10, "dd-mmmm-yyyy")) -> Estado de cuenta por Prestador al 30-septiembre-2025 | C6: 2384
B8: NIT del Prestador o Proveedor | C8: ='Detalle_ Radicacion'!C2 -> 0
B9: Razón social | C9: ='Detalle_ Radicacion'!D2 -> 0
B10: Corte de Radicación | C10: 45930
B11: Fecha de Elaboración | C11: 45937
B12: Modalidad | C12: Evento
B13: Cantidad de facturas radicadas al corte | D13: =COUNTA(_xlfn.UNIQUE('Detalle_ Radicacion'!J:J))-2 -> 0
B14: Descripción | C14: Vigencia 2024 | D14: Vigencia 2025
B15: A. (+) Total Radicado (Sin Devoluciones) | C15: =SUMIFS('Detalle_ Radicacion'!P:P,'Detalle_ Radicacion'!M:M, ">=01/01/2024",'Detalle_ Radicacion'!M:M, "<=31/12/2024") -> 0 | D15: =SUMIFS('Detalle_ Radicacion'!P:P,'Detalle_ Radicacion'!M:M, ">=01/01/2025",'Detalle_ Radicacion'!M:M, "<=31/12/2025") -> 0 | E15: =SUM(C15:D15) -> 0
B16: A1. Radicación corriente | C16: 0 | D16: =+SUMIF('Detalle_ Radicacion'!N:N,"0 a 30 dí­as",'Detalle_ Radicacion'!P:P)+SUMIF('Detalle_ Radicacion'!N:N,"31 a 45 dí­as",'Detalle_ Radicacion'!P:P)+SUMIF('Detalle_ Radicacion'!N:N,"46 a 60 dí­as",'Detalle_ Radicacion'!P:P) -> 0 | E16: =SUM(C16:D16) -> 0
B17: A2. Radicado no corriente | C17: =+C15 -> 0 | D17: =+D15-D16 -> 0 | E17: =SUM(C17:D17) -> 0
B18: B.(-) Sin Respuesta a glosa o aceptado | C18: =SUMIFS('Detalle_ Radicacion'!AD:AD,'Detalle_ Radicacion'!M:M, ">=01/01/2024",'Detalle_ Radicacion'!M:M, "<=31/12/2024") -> 0 | D18: =SUMIFS('Detalle_ Radicacion'!AD:AD,'Detalle_ Radicacion'!M:M, ">=01/01/2025",'Detalle_ Radicacion'!M:M, "<=31/12/2025") -> 0 | E18: =SUM(C18:D18) -> 0
B19: C.(-) Valor Pagado | C19: =SUMIFS('Detalle_ Radicacion'!AH:AH,'Detalle_ Radicacion'!M:M, ">=01/01/2024",'Detalle_ Radicacion'!M:M, "<=31/12/2024") -> 0 | D19: =SUMIFS('Detalle_ Radicacion'!AH:AH,'Detalle_ Radicacion'!M:M, ">=01/01/2025",'Detalle_ Radicacion'!M:M, "<=31/12/2025") -> 0 | E19: =SUM(C19:D19) -> 0
B20: C1. Vr por Aplicar Pago a factura | C20: =+SUMIFS('Detalle_ Radicacion'!AO:AO,'Detalle_ Radicacion'!N:N, "<01/01/2024",'Detalle_ Radicacion'!AO:AO,"<0") -> 0 | D20: =SUMIFS('Detalle_ Radicacion'!AO:AO,'Detalle_ Radicacion'!N:N, "<01/01/2025",'Detalle_ Radicacion'!AO:AO,"<0") -> 0 | E20: =SUM(C20:D20) -> 0
B21: C2. Vr Pago bajo factura | C21: =+C19-C20 -> 0 | D21: =+D19-D20 -> 0 | E21: =SUM(C21:D21) -> 0
B22: D. Anticipo Medico (Pendiente de legalizar) | C22: 0 | D22: 0 | E22: =SUM(C22:D22) -> 0
B23: E. (=) Estado Saldo (A-A1-B-C) | C23: =+C15-C16-C18-C19 -> 0 | D23: =+D15-D16-D18-D19 -> 0 | E23: =SUM(C23:D23) -> 0
B24: F. (-) Valor Ratificado Glosa | C24: =SUMIFS('Detalle_ Radicacion'!AF:AF,'Detalle_ Radicacion'!M:M, ">=01/01/2024",'Detalle_ Radicacion'!M:M, "<=31/12/2024") -> 0 | D24: =SUMIFS('Detalle_ Radicacion'!AF:AF, 'Detalle_ Radicacion'!N:N, "61 a 90 dí­as", 'Detalle_ Radicacion'!M:M, ">=01/01/2025", 'Detalle_ Radicacion'!M:M, "<=31/12/2025") +SUMIFS('Detalle_ Radicacion'!AF:AF, 'Detalle_ Radicacion'!N:N, "91 a 120 dí­as", 'Detalle_ Radicacion'!M:M, ">=01/01/2025", 'Detalle_ Radicacion'!M:M, "<=31/12/2025") +SUMIFS('Detalle_ Radicacion'!AF:AF, 'Detalle_ Radicacion'!N:N, "121 a 150 dí­as", 'Detalle_ Radicacion'!M:M, ">=01/01/2025", 'Detalle_ Radicacion'!M:M, "<=31/12/2025") +SUMIFS('Detalle_ Radicacion'!AF:AF, 'Detalle_ Radicacion'!N:N, "151 a 180 dí­as", 'Detalle_ Radicacion'!M:M, ">=01/01/2025", 'Detalle_ Radicacion'!M:M, "<=31/12/2025") +SUMIFS('Detalle_ Radicacion'!AF:AF, 'Detalle_ Radicacion'!N:N, "Mayor a 180 dí­as", 'Detalle_ Radicacion'!M:M, ">=01/01/2025", 'Detalle_ Radicacion'!M:M, "<=31/12/2025") -> 0 | E24: =SUM(C24:D24) -> 0
B25: G. (=) Saldo Sin Glosas (E-F) | C25: =+C23-C24 -> 0 | D25: =+D23-D24 -> 0 | E25: =SUM(C25:D25) -> 0
B26: Nota1: en el literal G si el saldo refleja valor negativo indica que no es procedente liberar saldo por concepto de glosas viegentes | D26: Elaborado por: | E26: Yimer Paez
B27: Nota 2: El Presente formato no constituye pago obligación y por tanto no puede ser tomado como exigibilidad y valor definitivo; ya que las facturas están sujetas a un proceso de auditoría de cuentas médicas. | D27: Cargo: | E27: Profesional
B28: Nota 3: En los casos que registran valor ratificado de glosas; estan sujetos a variación conforme a las respuesta de glosas efectuadas en la plataforma. | D28: Coordinación de conciliación y cartera
B29: Nota 4: La información contenida en el presente formato esta elaborado a la fecha de corte de radicación y no contempla la facturación en estado devuelta.
D30: Dirección administrativa y Financiera de la Gerencia de Servicios de Salud FOMAG
B31: Nota 5: Para el item C1 corresponde a facturacion a la que se realizó giro previo y por devoluciones sustentadas no se cuenta con valores para aplicar.

Sheet Detalle_ Radicacion
A1: id | B1: modalidad_pago | C1: nit | D1: nom_prestador | E1: tipo_red | F1: departamento | G1: municipio | H1: prefijo | I1: factura | J1: prefijo_factura | K1: mes_radicacion | L1: estado_aplicacion | M1: fecha_radicacion | N1: rango_dias | O1: fecha_factura | P1: valor_factura | Q1: valor_iva | R1: nota_credito | S1: valor_glosa_inicial | T1: valor_no_glosado_inicial | U1: valor_aceptado_primera_respuesta | V1: valor_levantado_primera_respuesta | W1: valor_ratificado_primera_respuesta | X1: valor_aceptado_segunda_respuesta | Y1: valor_levantado_segunda_respuesta | Z1: valor_ratificado_segunda_respuesta | AA1: valor_aceptado_conciliacion | AB1: valor_levantado_conciliacion | AC1: valor_ratificado_conciliacion | AD1: Valor_actual_aceptado | AE1: valor_actual_reconocido | AF1: valor_final_ratificado | AG1: En_tramite | AH1: valor_pagado | AI1: porcentaje_pago | AJ1: estado | AK1: voucher | AL1: feccha_pago | AM1: Estado_Saldo | AN1: Saldo_Sin_Glosas | AO1: Estado_de_Auditoria | AP1: Estado_Aplicacion_Pagos | AQ1: Porc_Pagos_Aplicado
